detdevlib/models/__init__.py
detdevlib/models/api.py
detdevlib_models-0.3.2.dist-info/METADATA
detdevlib_models-0.3.2.dist-info/WHEEL
detdevlib_models-0.3.2.dist-info/RECORD
