Metadata-Version: 2.4
Name: detdevlib-models
Version: 0.3.2
Summary: Reusable Model API factory for DET projects.
Author: Robert Mertens
Author-email: r.mertens@det.nl
Requires-Python: >=3.11,<4.0
Classifier: Programming Language :: Python :: 3
Classifier: Programming Language :: Python :: 3.11
Classifier: Programming Language :: Python :: 3.12
Classifier: Programming Language :: Python :: 3.13
Classifier: Programming Language :: Python :: 3.14
Requires-Dist: fastapi (>=0.116.1,<0.117.0)
Requires-Dist: httpx (>=0.28.1,<0.29.0)
Requires-Dist: numpy (>=2.3.2,<3.0.0)
Requires-Dist: pandas (>=2.3.2,<3.0.0)
Requires-Dist: plotly (>=6.3.0,<7.0.0)
Requires-Dist: pydantic (>=2.11.7,<3.0.0)
